magia_ip/__init__.py
magia_ip-0.0.1.dist-info/LICENSE
magia_ip-0.0.1.dist-info/METADATA
magia_ip-0.0.1.dist-info/WHEEL
magia_ip-0.0.1.dist-info/RECORD
