Metadata-Version: 2.1
Name: magia-ip
Version: 0.0.1
Summary: IP libraries designed with Magia
License: LICENSE
Keywords: Verilog HDL,SystemVerilog,Synthesizable,RTL,HDL,Hardware Description Language,Code Generation,FPGA,ASIC,EDA,RTL Design
Author: khwong-c64
Author-email: kin.hin.wong.c@gmail.com
Requires-Python: >=3.9,<4.0
Classifier: Development Status :: 3 - Alpha
Classifier: License :: OSI Approved :: MIT License
Classifier: License :: Other/Proprietary License
Classifier: Programming Language :: Python
Classifier: Programming Language :: Python :: 3
Classifier: Programming Language :: Python :: 3.9
Classifier: Programming Language :: Python :: 3.10
Classifier: Programming Language :: Python :: 3.11
Classifier: Programming Language :: Python :: 3.12
Requires-Dist: magia-hdl (>=0.4,<0.5)
Project-URL: Repository, https://github.com/magia-hdl/magia-ip
